LICENSE
MANIFEST.in
README.md
package.json
setup.py
date_range_filter/__init__.py
date_range_filter/_imports_.py
date_range_filter/date_range_filter.min.js
date_range_filter/date_range_filter.min.js.map
date_range_filter/date_range_filter.py
date_range_filter/metadata.json
date_range_filter/package-info.json
date_range_filter.egg-info/PKG-INFO
date_range_filter.egg-info/SOURCES.txt
date_range_filter.egg-info/dependency_links.txt
date_range_filter.egg-info/top_level.txt