Metadata-Version: 2.1
Name: date-range-filter
Version: 0.0.1a0
Summary:  pick the time filter and range filter
Home-page: UNKNOWN
Author: Kalimuthu Periyasamy <1995kalimuthu@gmail.com>
License: MIT
Platform: UNKNOWN
Classifier: Framework :: Dash
